Workbook

Sheet IS
A1: Line Item | B1: 2023A | C1: 2024A | D1: 2025E
A2: Revenue | B2: 100000 | C2: 120000 | D2: 150000
A3: Cost of Goods Sold | B3: 40000 | C3: 48000 | D3: 60000
A4: Gross Profit | B4: =B2-B3 | C4: =C2-C3 | D4: =D2-D3
A5: SG&A Expense | B5: 20000 | C5: 24000 | D5: 30000
A6: EBITDA | B6: =B4-B5 | C6: =C4-C5 | D6: =D4-D5
A7: Depreciation & Amortization | B7: 5000 | C7: 6000 | D7: 7500
A8: EBIT | B8: =B6-B7 | C8: =C6-C7 | D8: =D6-D7
A9: Interest Expense | B9: 2000 | C9: 1800 | D9: 1500
A10: EBT | B10: =B8-B9 | C10: =C8-C9 | D10: =D8-D9
A11: Tax | B11: =B10*0.25 | C11: =C10*0.25 | D11: =D10*0.25
A12: Net Income | B12: =B10-B11 | C12: =C10-C11 | D12: =D10-D11

Sheet BS
A1: Line Item | B1: 2023A | C1: 2024A | D1: 2025E
A2: Cash & Cash Equivalents | B2: =CF!B10 | C2: =CF!C10 | D2: =CF!D10
A3: Accounts Receivable | B3: 15000 | C3: 18000 | D3: 22500
A4: Inventory | B4: 10000 | C4: 12000 | D4: 15000
A5: Current Assets | B5: =SUM(B2:B4) | C5: =SUM(C2:C4) | D5: =SUM(D2:D4)
A6: Property, Plant & Equipment | B6: 50000 | C6: 55000 | D6: 60000
A7: Total Assets | B7: =B5+B6 | C7: =C5+C6 | D7: =D5+D6
A8: Accounts Payable | B8: 8000 | C8: 9600 | D8: 12000
A9: Long Term Debt | B9: 25000 | C9: 20000 | D9: 15000
A10: Total Liabilities | B10: =B8+B9 | C10: =C8+C9 | D10: =D8+D9
A11: Common Stock | B11: 20000 | C11: 20000 | D11: 20000
A12: Retained Earnings | B12: 22000 | C12: =B12+IS!C12 | D12: =C12+IS!D12
A13: Total Liabilities & Equity | B13: =B10+B11+B12 | C13: =C10+C11+C12 | D13: =D10+D11+D12

Sheet CF
A1: Line Item | B1: 2023A | C1: 2024A | D1: 2025E | W1: CIRCULAR_INTENTIONAL | X1: =CF!X1+1
A2: Net Income | B2: =IS!B12 | C2: =IS!C12 | D2: =IS!D12
A3: Depreciation | B3: =IS!B7 | C3: =IS!C7 | D3: =IS!D7
A4: Change in Working Capital | B4: -2000 | C4: -2500 | D4: -3000
A5: Cash Flow from Operations | B5: =SUM(B2:B4) | C5: =SUM(C2:C4) | D5: =SUM(D2:D4)
A6: Capital Expenditures | B6: -5000 | C6: -6000 | D6: -7000
A7: Cash Flow from Investing | B7: =B6 | C7: =C6 | D7: =D6
A8: Debt Repayment | B8: -5000 | C8: -5000 | D8: -5000
A9: Cash Flow from Financing | B9: =B8 | C9: =C8 | D9: =D8
A10: Ending Cash | B10: =B5+B7+B9 | C10: =C5+C7+C9 | D10: =D5+D7+D9

Sheet Comps
A1: Company | B1: Category | C1: Revenue | D1: EBITDA | E1: EV | F1: EV/EBITDA
A2: Alpha Inc | B2: Software | C2: 50000 | D2: 15000 | E2: 150000 | F2: =E2/D2
A3: Beta Corp | B3: Hardware | C3: 80000 | D3: 16000 | E3: 120000 | F3: =E3/D3
A4: Gamma Ltd | B4: Software | C4: 45000 | D4: 13500 | E4: 135000 | F4: =E4/D4
A5: Delta LLC | B5: Hardware | C5: 70000 | D5: 14000 | E5: 98000 | F5: =E5/D5
A6: Total / Average | B6: All | C6: =SUM(C2:C5) | D6: =SUM(D2:D5) | E6: =SUM(E2:E5) | F6: =AVERAGE(F2:F5)
A10: Category | B10: Total Revenue (SUMIFS) | C10: Total EBITDA (SUMIFS)
A11: Software | B11: =SUMIFS(C$2:C$5, B$2:B$5, "Software") | C11: =SUMIFS(D$2:D$5, B$2:B$5, "Software")
A12: Hardware | B12: =SUMIFS(C$2:C$5, B$2:B$5, "Hardware") | C12: =SUMIFS(D$2:D$5, B$2:B$5, "Hardware")
A13: Summary Total | B13: =SUM(B11:B12) | C13: =SUM(C11:C12)
